codificador.v
module codificador_em_morse (a, b, c, d, s1, s2, s3, s4, s5, reset, ready);
    input wire a, b, c, d, reset, ready;
    output reg s1, s2, s3, s4, s5; //Saidas codificadas em morse//


    always @(*) begin
      if (reset) begin
        s1 = 0;
        s2 = 0;
        s3 = 0;
        s4 = 0;
        s5 = 0;
      end
      else if (ready) begin
        s1 = (~b & c) | (b & ~c) | (~a & ~b & d);
        s2 = (~b & c) | (c & ~d) | (b & ~c);
        s3 = (b) | (c & d);
        s4 = (b) | (a & ~d);
        s5 = (a) | (b & d) | (b & c);
      end
    end
endmodule

testebench.v
`include "codificador.v"
module testbench();
  reg a, b, c, d, reset, ready;
  wire s1, s2, s3, s4, s5;
  codificador_em_morse codificador_aux(.a(a), .b(b), .c(c), .d(d), .s1(s1), .s2(s2), .s3(s3), .s4(s4), .s5(s5), .reset(reset), .ready(ready));
  initial begin
    $dumpfile("testdump.vcd");
    $dumpvars(0 ,testbench);
    $display("Testbech do codificador em morse iniciado!");
    $monitor("Alteração detectada! -> %b%b%b%b = %b %b %b %b %b", a,b,c,d,s1,s2,s3,s4,s5);
  end

  initial begin
          reset = 1;
     #1;  reset = 0;
     #1;  ready = 0; a = 0; b = 0; c = 0; d = 0; ready = 1; // 0
     #1;  ready = 0; a = 0; b = 0; c = 0; d = 1; ready = 1; // 1
     #1;  ready = 0; a = 0; b = 0; c = 1; d = 0; ready = 1; // 2
     #1;  ready = 0; a = 0; b = 0; c = 1; d = 1; ready = 1; // 3
     #1;  ready = 0; a = 0; b = 1; c = 0; d = 0; ready = 1; // 4
     #1;  ready = 0; a = 0; b = 1; c = 0; d = 1; ready = 1; // 5
     #1;  ready = 0; a = 0; b = 1; c = 1; d = 0; ready = 1; // 6
     #1;  ready = 0; a = 0; b = 1; c = 1; d = 1; ready = 1; // 7
     #1;  ready = 0; a = 1; b = 0; c = 0; d = 0; ready = 1; // 8
     #1;  ready = 0; a = 1; b = 0; c = 0; d = 1; ready = 1; // 9
     $finish;
  end
endmodule

testdump.vcd
$date
	Wed Oct 10 20:57:48 2018
$end
$version
	Icarus Verilog
$end
$timescale
	1s
$end
$scope module testbench $end
$var wire 1 ! s5 $end
$var wire 1 " s4 $end
$var wire 1 # s3 $end
$var wire 1 $ s2 $end
$var wire 1 % s1 $end
$var reg 1 & a $end
$var reg 1 ' b $end
$var reg 1 ( c $end
$var reg 1 ) d $end
$var reg 1 * ready $end
$var reg 1 + reset $end
$scope module codificador_aux $end
$var wire 1 & a $end
$var wire 1 ' b $end
$var wire 1 ( c $end
$var wire 1 ) d $end
$var wire 1 * ready $end
$var wire 1 + reset $end
$var reg 1 % s1 $end
$var reg 1 $ s2 $end
$var reg 1 # s3 $end
$var reg 1 " s4 $end
$var reg 1 ! s5 $end
$upscope $end
$upscope $end
$enddefinitions $end
#0
$dumpvars
1+
x*
x)
x(
x'
x&
0%
0$
0#
0"
0!
$end
#1
0+
#2
0)
0(
0'
0&
1*
#3
1%
1)
1*
#4
1$
0)
1(
1*
#5
1#
1)
1*
#6
1"
0)
0(
1'
1*
#7
1!
1)
1*
#8
0%
0)
1(
1*
#9
0$
1)
1*
#10
0#
0)
0(
0'
1&
1*
#11
0"
1)
1*
