codificador.v
module codificador_em_morse (a, b, c, d, s1, reset, ready);
    input wire a, b, c, d, reset, ready;
    output reg [4:0] s1; //Saidas codificadas em morse//


    always @(*) begin
      if (reset) begin
        s1[4] = 0;
        s1[3] = 0;
        s1[2] = 0;
        s1[1] = 0;
        s1[0] = 0;
      end
      else if (ready) begin
        s1[4] = (~b & c) | (b & ~c) | (~a & ~b & d);
        s1[3] = (~b & c) | (c & ~d) | (b & ~c);
        s1[2] = (b) | (c & d);
        s1[1] = (b) | (a & ~d);
        s1[0] = (a) | (b & d) | (b & c);
      end
    end
endmodule

testbench.v
`include "codificador.v"
module testbench();
  reg a, b, c, d, reset, ready;
  wire[4:0] s1;
  codificador_em_morse codificador_aux(.a(a), .b(b), .c(c), .d(d), .s1(s1), .reset(reset), .ready(ready));
  initial begin
    $dumpfile("testdump.vcd");
    $dumpvars(0 ,testbench);
    $display("Testbech do codificador em morse iniciado!");
    $monitor("Alteração detectada! -> %b%b%b%b = %b %b %b %b %b", a,b,c,d,s1[4],s1[3],s1[2],s1[1],s1[0]);
  end

  initial begin
          reset = 1;
     #1;  reset = 0;
     #1;  ready = 0; a = 0; b = 0; c = 0; d = 0; ready = 1; // 0
     #1;  ready = 0; a = 0; b = 0; c = 0; d = 1; ready = 1; // 1
     #1;  ready = 0; a = 0; b = 0; c = 1; d = 0; ready = 1; // 2
     #1;  ready = 0; a = 0; b = 0; c = 1; d = 1; ready = 1; // 3
     #1;  ready = 0; a = 0; b = 1; c = 0; d = 0; ready = 1; // 4
     #1;  ready = 0; a = 0; b = 1; c = 0; d = 1; ready = 1; // 5
     #1;  ready = 0; a = 0; b = 1; c = 1; d = 0; ready = 1; // 6
     #1;  ready = 0; a = 0; b = 1; c = 1; d = 1; ready = 1; // 7
     #1;  ready = 0; a = 1; b = 0; c = 0; d = 0; ready = 1; // 8
     #1;  ready = 0; a = 1; b = 0; c = 0; d = 1; ready = 1; // 9
     $finish;
  end
endmodule

testdump.vcd
$date
	Thu Oct 11 00:26:35 2018
$end
$version
	Icarus Verilog
$end
$timescale
	1s
$end
$scope module testbench $end
$var wire 5 ! s1 [4:0] $end
$var reg 1 " a $end
$var reg 1 # b $end
$var reg 1 $ c $end
$var reg 1 % d $end
$var reg 1 & ready $end
$var reg 1 ' reset $end
$scope module codificador_aux $end
$var wire 1 " a $end
$var wire 1 # b $end
$var wire 1 $ c $end
$var wire 1 % d $end
$var wire 1 & ready $end
$var wire 1 ' reset $end
$var reg 5 ( s1 [4:0] $end
$upscope $end
$upscope $end
$enddefinitions $end
#0
$dumpvars
b0 (
1'
x&
x%
x$
x#
x"
b0 !
$end
#1
0'
#2
0%
0$
0#
0"
1&
#3
b10000 !
b10000 (
1%
1&
#4
b11000 !
b11000 (
0%
1$
1&
#5
b11100 !
b11100 (
1%
1&
#6
b11110 !
b11110 (
0%
0$
1#
1&
#7
b11111 !
b11111 (
1%
1&
#8
b1111 !
b1111 (
0%
1$
1&
#9
b111 !
b111 (
1%
1&
#10
b11 !
b11 (
0%
0$
0#
1"
1&
#11
b1 !
b1 (
1%
1&
